{
    "actors": [
        "MORGAN FREEMAN",
        "ROBIN WILLIAMS",
        "SAMUEL L JACKSON",
        "KEANU REEVES",
        "BETTY WHITE",
        "DENZEL WASHINGTON",
        "DANNY DEVITO",
        "JACKIE CHAN",
        "MICHAEL J FOX",
        "EDDIE MURPHY",
        "BRUCE WILLIS",
        "NICOLAS CAGE",
        "BRUCE LEE",
        "SANDRA BULLOCK",
        "HARRISON FORD",
        "TOM HANKS",
        "JAMES EARL JONES",
        "SEAN CONNERY",
        "ROBERT DOWNEY JR",
        "MATTHEW MCCONAUGHEY",
        "HUMPHREY BOGART",
        "JACK NICHOLSON",
        "ROBERT DE NIRO",
        "ANTHONY HOPKINS",
        "GENE HACKMAN",
        "MARLON BRANDO",
        "CARY GRANT",
        "DUSTIN HOFFMAN",
        "JOHN LITHGOW",
        "ROBERT REDFORD",
        "BILL PAXTON",
        "ALAN RICKMAN",
        "AMITABH BACHCHAN",
        "SHAH RUKH KHAN",
        "AAMIR KHAN",
        "SALMAN KHAN",
        "DILIP KUMAR",
        "KAMAL HAASAN"
    ],
    "scientists": [
        "ISAAC NEWTON",
        "ALBERT EINSTEIN",
        "MARIE CURIE",
        "LOUIS PASTEUR",
        "CHARLES DARWIN",
        "NIKOLA TESLA",
        "GALILEO GALILEI",
        "DMITRI MENDELEEV",
        "JOHANNES KEPLER",
        "MICHAEL FARADAY",
        "MAX PLANCK",
        "NICOLAUS COPERNICUS",
        "ALAN TURING",
        "ROSALIND FRANKLIN",
        "STEPHEN HAWKING",
        "ARCHIMEDES",
        "LEONARDO DA VINCI",
        "TIM BERNERS-LEE",
        "THOMAS ALVA EDISON",
        "GREGOR MENDEL",
        "ADA LOVELACE",
        "PYTHAGORAS",
        "APJ ABDUL KALAM",
        "CV RAMAN",
        "HOMI J BHABHA",
        "VIKRAM SARABHAI",
        "SRINIVASA RAMANUJAN",
        "JAGADISH CHANDRA BOSE",
        "SATYENDRA NATH BOSE",
        "ARYABHATA",
        "MEGHNAD SAHA",
        "SALIM ALI"
    ],
    "athletes": [
        "MICHAEL JORDAN",
        "MUHAMMAD ALI",
        "PELE",
        "USAIN BOLT",
        "MICHAEL PHELPS",
        "WAYNE GRETZKY",
        "JIM THORPE",
        "CRISTIANO RONALDO",
        "BABE RUTH",
        "JESSE OWENS",
        "JACKIE ROBINSON",
        "ROGER FEDERER",
        "NADIA COMANECI",
        "SIR STEVE REDGRAVE",
        "SACHIN TENDULKAR",
        "VIRAT KOHLI",
        "MS DHONI",
        "DHYAN CHAND",
        "MILKHA SINGH",
        "NEERAJ CHOPRA",
        "PT USHA",
        "PV SINDHU",
        "MARY KOM",
        "SUNIL CHHETRI",
        "VISWANATHAN ANAND"
    ],
    "politicians": [
        "ABRAHAM LINCOLN",
        "MAHATMA GANDHI",
        "WINSTON CHURCHILL",
        "MARTIN LUTHER KING JR",
        "NELSON MANDELA",
        "JULIUS CAESAR",
        "ALEXANDER THE GREAT",
        "QUEEN ELIZABETH II",
        "GEORGE WASHINGTON",
        "FRANKLIN D ROOSEVELT",
        "NAPOLEON BONAPARTE",
        "CLEOPATRA",
        "MARGARET THATCHER",
        "MOTHER TERESA",
        "RONALD REAGAN",
        "THOMAS JEFFERSON",
        "JOHN F KENNEDY",
        "THEODORE ROOSEVELT",
        "DWIGHT D EISENHOWER",
        "JAWAHARLAL NEHRU",
        "SARDAR PATEL",
        "BR AMBEDKAR",
        "SUBHAS CHANDRA BOSE",
        "INDIRA GANDHI",
        "NARENDRA MODI"
    ],
    "space": [
        "NEIL ARMSTRONG",
        "BUZZ ALDRIN",
        "YURI GAGARIN",
        "VALENTINA TERESHKOVA",
        "JOHN GLENN",
        "SALLY RIDE",
        "ALAN SHEPARD",
        "MICHAEL COLLINS",
        "MAE JEMISON",
        "KALPANA CHAWLA",
        "RAKESH SHARMA",
        "KOICHI WAKA TA",
        "SCOTT KELLY",
        "PEGGY WHITSON",
        "CHRIS HADFIELD",
        "ANDROMEDA GALAXY",
        "HALLEYS COMET",
        "MOUNT OLYMPUS MARS",
        "SATURN RINGS",
        "VOYAGER PROBE",
        "HUBBLE TELESCOPE"
    ],
    "landmarks": [
        "GREAT WALL OF CHINA",
        "TAJ MAHAL",
        "STATUE OF LIBERTY",
        "COLOSSEUM",
        "MACHU PICCHU",
        "PYRAMIDS OF GIZA",
        "STONEHENGE",
        "ACROPOLIS",
        "PETRA",
        "ANGKOR WAT",
        "EASTER ISLAND MOAI",
        "CHRIST THE REDEEMER",
        "EIFFEL TOWER",
        "BIG BEN",
        "GOLDEN GATE BRIDGE"
    ]
}